dynare/__init__.py
dynare/distributions.py
dynare/dynare.py
dynare/dynare_context.py
dynare/errors.py
dynare/juliapkg.json
dynare/workspace.py
dynare_python-0.1.0.dist-info/LICENSE.md
dynare_python-0.1.0.dist-info/METADATA
dynare_python-0.1.0.dist-info/WHEEL
dynare_python-0.1.0.dist-info/top_level.txt
dynare_python-0.1.0.dist-info/RECORD
